porch_pirate-0.0.1.data/scripts/porch-pirate
porchpirate/__init__.py
porchpirate/porchpirate.py
porch_pirate-0.0.1.dist-info/LICENSE
porch_pirate-0.0.1.dist-info/METADATA
porch_pirate-0.0.1.dist-info/WHEEL
porch_pirate-0.0.1.dist-info/top_level.txt
porch_pirate-0.0.1.dist-info/RECORD
