Metadata-Version: 2.1
Name: porch-pirate
Version: 0.0.1
Summary: Porch Pirate is the most comprehensive recon / OSINT client and framework for Postman that facilitates the automated discovery and exploitation of API endpoints and secrets committed to workspaces, collections, requests, users and teams. Porch Pirate can be used as a client or be incorporated into your own applications.
Home-page: https://github.com/mandconsultinggroup/porch-pirate
Author: Mand Consulting Group / Dominik Penner (zer0pwn) / Jake Bolam (@xixasec)
Author-email: zer0pwn@riseup.net
Keywords: porchpirate porch pirate porch-pirate postman postmaniac postleaks osint recon enumeration secrets loot treasure
License-File: LICENSE
Requires-Dist: requests
